{
	"products": [
    {
		"id": 87481417737,
		"title": "1cm Holographic Choker",
		"body_html": "<p>Metallic style holographic choker with a 1cm width. </p><p>Rose gold finish <br>Holographic <br>1cm </p>",
		"vendor": "Impulse Fashion Accessories",
		"product_type": "JEWELLERY",
		"created_at": "2017-11-24T18:16:09+00:00",
		"handle": "1cm-holographic-choker-mid-pink-jl6805",
		"updated_at": "2018-06-20T09:44:22+01:00",
		"published_at": null,
		"template_suffix": null,
		"tags": ".5, 50% Off, Accessories, APItagIndexRemoveThis, Chokers, Going Out Looks, ISAWITFIRST.com, METALLIC, Mid Pink, Necklace, ONE SIZE, Pcat-Accessories, RT_0, Sale, Sale:SALE:New In Accessories, Scat-Jewellery, XP_90",
		"published_scope": "web",
		"variants": [
    {
			"id": 956458434569,
			"product_id": 87481417737,
			"title": "OS / RED",
			"price": "1.00",
			"sku": "A17W-2600014239-RLD-OS",
			"position": 1,
			"inventory_policy": "deny",
			"compare_at_price": "4.00",
			"fulfillment_service": "manual",
			"inventory_management": "shopify",
			"option1": "OS",
			"option2": "RED",
			"option3": null,
			"created_at": "2017-11-26T10:34:37+00:00",
			"updated_at": "2018-06-12T20:44:35+01:00",
			"taxable": false,
			"barcode": null,
			"grams": 100,
			"image_id": null,
			"inventory_quantity": 0,
			"weight": 100,
			"weight_unit": "g",
			"inventory_item_id": 971860705289,
			"tax_code": "",
			"old_inventory_quantity": 0,
			"requires_shipping": true
    }
  ],
		"options": [
    {
			"id": 137336389641,
			"product_id": 87481417737,
			"name": "SIZE",
			"position": 1,
			"values": ["OS"]
    },
    {
			"id": 139125882889,
			"product_id": 87481417737,
			"name": "Colour",
			"position": 2,
			"values": ["RED"]
    }
  ],
		"images": [
    {
			"id": 4306280317046,
			"product_id": 87481417737,
			"position": 1,
			"created_at": "2018-06-20T03:07:29+01:00",
			"updated_at": "2018-06-20T03:07:29+01:00",
			"alt": null,
			"width": 1399,
			"height": 2098,
			"src": "https://cdn.shopify.com/s/files/1/1962/2013/products/A17W-2600014239-RLD-OS0217-M1.jpg?v=1529460449",
			"variant_ids": []
    },
    {
			"id": 4306280349814,
			"product_id": 87481417737,
			"position": 2,
			"created_at": "2018-06-20T03:07:29+01:00",
			"updated_at": "2018-06-20T03:07:29+01:00",
			"alt": null,
			"width": 1399,
			"height": 2098,
			"src": "https://cdn.shopify.com/s/files/1/1962/2013/products/A17W-2600014239-RLD-2.jpg?v=1529460449",
			"variant_ids": []
    }
    ],
		"image": {
			"id": 4306280317046,
			"product_id": 87481417737,
			"position": 1,
			"created_at": "2018-06-20T03:07:29+01:00",
			"updated_at": "2018-06-20T03:07:29+01:00",
			"alt": null,
			"width": 1399,
			"height": 2098,
			"src": "https://cdn.shopify.com/s/files/1/1962/2013/products/A17W-2600014239-RLD-OS0217-M1.jpg?v=1529460449",
			"variant_ids": []
		}
    },
    {
		"id": 33553383433,
		"title": "1CM TINSEL CHOKER WITH CENTRE RING",
		"body_html": "<p>Tinsel choker featuring a gold centre ring detail.</p><p>Tinsel choker<br>Gold centre ring detail<br></p>",
		"vendor": "Impulse Fashion Accessories",
		"product_type": "JEWELLERY",
		"created_at": "2017-10-11T16:33:03+01:00",
		"handle": "1cm-tinsel-choker-with-centre-ring-black-jl6999",
		"updated_at": "2018-06-20T03:35:09+01:00",
		"published_at": null,
		"template_suffix": null,
		"tags": "0.3 Off, Accessories, APItagIndexRemoveThis, Black, Chokers, Fp, ISAWITFIRST.com, Jewellery - From £2, New In Accessories, One Size, Party, Pcat-Accessories, RT_0, Scat-Jewellery, Sp3, XP_120",
		"published_scope": "web",
		"variants": [
      {
			"id": 292056465417,
			"product_id": 33553383433,
			"title": "OS / BLACK",
			"price": "4.00",
			"sku": "A17W-2600014596-BCK-OS",
			"position": 1,
			"inventory_policy": "deny",
			"compare_at_price": null,
			"fulfillment_service": "manual",
			"inventory_management": "shopify",
			"option1": "OS",
			"option2": "BLACK",
			"option3": null,
			"created_at": "2017-10-11T16:33:04+01:00",
			"updated_at": "2018-04-19T09:32:10+01:00",
			"taxable": false,
			"barcode": "5057710001945",
			"grams": 100,
			"image_id": null,
			"inventory_quantity": 0,
			"weight": 100,
			"weight_unit": "g",
			"inventory_item_id": 278664609801,
			"tax_code": "",
			"old_inventory_quantity": 0,
			"requires_shipping": true
      }
    ],
		"options": [
      {
        "id": 47740583945,
        "product_id": 33553383433,
        "name": "SIZE",
        "position": 1,
        "values": ["OS"]
      },
      {
        "id": 124491431945,
        "product_id": 33553383433,
        "name": "Colour",
        "position": 2,
        "values": ["BLACK"]
      }
    ],
		"images": [
      {
			"id": 4305804853366,
			"product_id": 33553383433,
			"position": 1,
			"created_at": "2018-06-20T02:46:05+01:00",
			"updated_at": "2018-06-20T02:46:05+01:00",
			"alt": null,
			"width": 1399,
			"height": 2098,
			"src": "https://cdn.shopify.com/s/files/1/1962/2013/products/A17W-2600014596-BCK-OS-1.jpg?v=1529459165",
			"variant_ids": []
      }
    ],
		"image": {
			"id": 4305804853366,
			"product_id": 33553383433,
			"position": 1,
			"created_at": "2018-06-20T02:46:05+01:00",
			"updated_at": "2018-06-20T02:46:05+01:00",
			"alt": null,
			"width": 1399,
			"height": 2098,
			"src": "https://cdn.shopify.com/s/files/1/1962/2013/products/A17W-2600014596-BCK-OS-1.jpg?v=1529459165",
			"variant_ids": []
		}
    },
    {
		"id": 24650252297,
		"title": "200cm Long Acrylic Plaid Scarf",
		"body_html": "<p>Stylish scarf featuring plaid detail, acrylic finish and 200cm length.</p><p>Plaid detail <br>Acrylic finish <br>200cm Length <br></p>",
		"vendor": "Impulse Fashion Accessories",
		"product_type": "Accessories",
		"created_at": "2017-10-05T17:03:14+01:00",
		"handle": "200cm-long-acrylic-plaid-scarf-multi-jl7053",
		"updated_at": "2018-06-20T03:34:48+01:00",
		"published_at": null,
		"template_suffix": "",
		"tags": "60% Off, Accessories, APItagIndexRemoveThis, Daywear, ISAWITFIRST.com, Multi, ONE SIZE, Pcat-Accessories, Puresale, RT_.02, Sale, Sale:SALE:New In Accessories, Scarves, Scat-Other, XP_311",
		"published_scope": "web",
		"variants": [
      {
			"id": 190262378505,
			"product_id": 24650252297,
			"title": "OS / MULTI",
			"price": "5.00",
			"sku": "A17W-2100014677-MTI-OS",
			"position": 1,
			"inventory_policy": "deny",
			"compare_at_price": "10.00",
			"fulfillment_service": "manual",
			"inventory_management": "shopify",
			"option1": "OS",
			"option2": "MULTI",
			"option3": null,
			"created_at": "2017-10-05T17:03:14+01:00",
			"updated_at": "2018-06-20T03:34:48+01:00",
			"taxable": false,
			"barcode": "5057710155754",
			"grams": 100,
			"image_id": null,
			"inventory_quantity": 0,
			"weight": 100,
			"weight_unit": "g",
			"inventory_item_id": 172791889929,
			"tax_code": "",
			"old_inventory_quantity": 0,
			"requires_shipping": true
      }
    ],
		"options": [
      {
			"id": 33555709961,
			"product_id": 24650252297,
			"name": "SIZE",
			"position": 1,
			"values": ["OS"]
      },
      {
			"id": 124489400329,
			"product_id": 24650252297,
			"name": "Colour",
			"position": 2,
			"values": ["MULTI"]
      }
    ],
		"images": [
      {
			"id": 4305768906870,
			"product_id": 24650252297,
			"position": 1,
			"created_at": "2018-06-20T02:44:34+01:00",
			"updated_at": "2018-06-20T02:44:34+01:00",
			"alt": null,
			"width": 1399,
			"height": 2098,
			"src": "https://cdn.shopify.com/s/files/1/1962/2013/products/A17W-2100014677-1.jpg?v=1529459074",
			"variant_ids": []
      }
    ],
		"image": {
			"id": 4305768906870,
			"product_id": 24650252297,
			"position": 1,
			"created_at": "2018-06-20T02:44:34+01:00",
			"updated_at": "2018-06-20T02:44:34+01:00",
			"alt": null,
			"width": 1399,
			"height": 2098,
			"src": "https://cdn.shopify.com/s/files/1/1962/2013/products/A17W-2100014677-1.jpg?v=1529459074",
			"variant_ids": []
		  }
    },
    {
		"id": 153086722057,
		"title": "3 Strap Mesh Bikini Bottom",
		"body_html": "<p>Prepare for poolside in these high waisted bikini bottoms. They feature a 3 strap mesh hem an an elasticated high waistband. These bikini bottoms are sold as an individual but are part of a matching set.</p><p>High waisted<br>3 strap detail<br>Mesh material</p>",
		"vendor": "PURE FASHION",
		"product_type": "SWIMWEAR",
		"created_at": "2018-01-17T16:58:10+00:00",
		"handle": "3-strap-mesh-bikini-bottom-black-jl3665",
		"updated_at": "2018-06-20T07:35:31+01:00",
		"published_at": "2018-06-20T07:35:31+01:00",
		"template_suffix": null,
		"tags": "12, 14, 6, 8, <£10, APItagIndexRemoveThis, Bikini, Black, Holiday, Holiday Shop, ISAWITFIRST.com, Mesh, Pcat-Swimwear, RT_0, Sale, Sale:SALE:New In Clothing, Scat-Swimsuit, Swimwear, XP_425",
		"published_scope": "web",
		"variants": [
      {
			"id": 1777486725129,
			"product_id": 153086722057,
			"title": "6 / BLACK",
			"price": "7.00",
			"sku": "S17W-4200008098-BCK-6",
			"position": 1,
			"inventory_policy": "deny",
			"compare_at_price": "15.00",
			"fulfillment_service": "manual",
			"inventory_management": "shopify",
			"option1": "6",
			"option2": "BLACK",
			"option3": null,
			"created_at": "2018-01-17T16:58:11+00:00",
			"updated_at": "2018-06-20T03:33:28+01:00",
			"taxable": false,
			"barcode": null,
			"grams": 100,
			"image_id": null,
			"inventory_quantity": 10,
			"weight": 100,
			"weight_unit": "g",
			"inventory_item_id": 1850689191945,
			"tax_code": "",
			"old_inventory_quantity": 10,
			"requires_shipping": true
      },
      {
			"id": 1777486757897,
			"product_id": 153086722057,
			"title": "8 / BLACK",
			"price": "12.00",
			"sku": "S17W-4200008098-BCK-8",
			"position": 2,
			"inventory_policy": "deny",
			"compare_at_price": null,
			"fulfillment_service": "manual",
			"inventory_management": "shopify",
			"option1": "8",
			"option2": "BLACK",
			"option3": null,
			"created_at": "2018-01-17T16:58:11+00:00",
			"updated_at": "2018-05-16T21:12:30+01:00",
			"taxable": false,
			"barcode": null,
			"grams": 100,
			"image_id": null,
			"inventory_quantity": 31,
			"weight": 100,
			"weight_unit": "g",
			"inventory_item_id": 1850689224713,
			"tax_code": "",
			"old_inventory_quantity": 31,
			"requires_shipping": true
      },
      {
			"id": 1777486790665,
			"product_id": 153086722057,
			"title": "10 / BLACK",
			"price": "12.00",
			"sku": "S17W-4200008098-BCK-10",
			"position": 3,
			"inventory_policy": "deny",
			"compare_at_price": null,
			"fulfillment_service": "manual",
			"inventory_management": "shopify",
			"option1": "10",
			"option2": "BLACK",
			"option3": null,
			"created_at": "2018-01-17T16:58:11+00:00",
			"updated_at": "2018-06-20T06:42:55+01:00",
			"taxable": false,
			"barcode": null,
			"grams": 100,
			"image_id": null,
			"inventory_quantity": 30,
			"weight": 100,
			"weight_unit": "g",
			"inventory_item_id": 1850689257481,
			"tax_code": "",
			"old_inventory_quantity": 30,
			"requires_shipping": true
      },
      {
			"id": 1777486823433,
			"product_id": 153086722057,
			"title": "12 / BLACK",
			"price": "12.00",
			"sku": "S17W-4200008098-BCK-12",
			"position": 4,
			"inventory_policy": "deny",
			"compare_at_price": null,
			"fulfillment_service": "manual",
			"inventory_management": "shopify",
			"option1": "12",
			"option2": "BLACK",
			"option3": null,
			"created_at": "2018-01-17T16:58:11+00:00",
			"updated_at": "2018-06-02T21:25:20+01:00",
			"taxable": false,
			"barcode": null,
			"grams": 100,
			"image_id": null,
			"inventory_quantity": 14,
			"weight": 100,
			"weight_unit": "g",
			"inventory_item_id": 1850689290249,
			"tax_code": "",
			"old_inventory_quantity": 14,
			"requires_shipping": true
      },
      {
			"id": 1777486856201,
			"product_id": 153086722057,
			"title": "14 / BLACK",
			"price": "12.00",
			"sku": "S17W-4200008098-BCK-14",
			"position": 5,
			"inventory_policy": "deny",
			"compare_at_price": null,
			"fulfillment_service": "manual",
			"inventory_management": "shopify",
			"option1": "14",
			"option2": "BLACK",
			"option3": null,
			"created_at": "2018-01-17T16:58:11+00:00",
			"updated_at": "2018-06-06T10:09:05+01:00",
			"taxable": false,
			"barcode": null,
			"grams": 100,
			"image_id": null,
			"inventory_quantity": 9,
			"weight": 100,
			"weight_unit": "g",
			"inventory_item_id": 1850689323017,
			"tax_code": "",
			"old_inventory_quantity": 9,
			"requires_shipping": true
      },
      {
			"id": 1777486888969,
			"product_id": 153086722057,
			"title": "16 / BLACK",
			"price": "7.00",
			"sku": "S17W-4200008098-BCK-16",
			"position": 6,
			"inventory_policy": "deny",
			"compare_at_price": "15.00",
			"fulfillment_service": "manual",
			"inventory_management": "shopify",
			"option1": "16",
			"option2": "BLACK",
			"option3": null,
			"created_at": "2018-01-17T16:58:11+00:00",
			"updated_at": "2018-06-20T03:33:28+01:00",
			"taxable": false,
			"barcode": null,
			"grams": 100,
			"image_id": null,
			"inventory_quantity": 0,
			"weight": 100,
			"weight_unit": "g",
			"inventory_item_id": 1850689355785,
			"tax_code": "",
			"old_inventory_quantity": 0,
			"requires_shipping": true
      }
    ],
		"options": [
      {
			"id": 230612860937,
			"product_id": 153086722057,
			"name": "SIZE",
			"position": 1,
			"values": ["6", "8", "10", "12", "14", "16"]
      },
      {
			"id": 1347042934902,
			"product_id": 153086722057,
			"name": "Colour",
			"position": 2,
			"values": ["BLACK"]
      }
    ],
		"images": [
      {
			"id": 4305653170294,
			"product_id": 153086722057,
			"position": 1,
			"created_at": "2018-06-20T02:39:33+01:00",
			"updated_at": "2018-06-20T02:39:33+01:00",
			"alt": null,
			"width": 1399,
			"height": 2098,
			"src": "https://cdn.shopify.com/s/files/1/1962/2013/products/S17W-4200008098-BCK-1.jpg?v=1529458773",
			"variant_ids": []
      },
      {
			"id": 4305653203062,
			"product_id": 153086722057,
			"position": 2,
			"created_at": "2018-06-20T02:39:33+01:00",
			"updated_at": "2018-06-20T02:39:33+01:00",
			"alt": null,
			"width": 1399,
			"height": 2098,
			"src": "https://cdn.shopify.com/s/files/1/1962/2013/products/S17W-4200008098-BCK-2.jpg?v=1529458773",
			"variant_ids": []
      }
    ],
		"image": {
			"id": 4305653170294,
			"product_id": 153086722057,
			"position": 1,
			"created_at": "2018-06-20T02:39:33+01:00",
			"updated_at": "2018-06-20T02:39:33+01:00",
			"alt": null,
			"width": 1399,
			"height": 2098,
			"src": "https://cdn.shopify.com/s/files/1/1962/2013/products/S17W-4200008098-BCK-1.jpg?v=1529458773",
			"variant_ids": []
		  }
    },
    {
		"id": 759791747190,
		"title": "3 Strap Mesh Bikini Bottom",
		"body_html": "<p>Catch those rays and top up that tan in this gorgeous 3 strap detail bikini bottom. Featuring a stylish mesh finish and high waisted fit. Team with our matching bikini top and cute sandals to compliment this look.</p><p>Bikini bottom <br>3 strap detail <br>Mesh finish <br>High waisted </p>",
		"vendor": "PURE FASHION",
		"product_type": "SWIMWEAR",
		"created_at": "2018-04-23T19:47:57+01:00",
		"handle": "3-strap-mesh-bikini-bottom-coral-jl3665",
		"updated_at": "2018-06-20T03:40:52+01:00",
		"published_at": "2018-06-14T14:37:42+01:00",
		"template_suffix": null,
		"tags": "12, 14, 6, 8, <£10, APItagIndexRemoveThis, Bikini, Coral, Holiday, Holiday Shop, ISAWITFIRST.com, Mesh, Pcat-Swimwear, RED, RT_?, Sale, Sale:/Collections/New-In, SALE:New In Clothing, Scat-Swimsuit, Summer Shop Aug, Swimwear, VM199, XP_425",
		"published_scope": "web",
		"variants": [
      {
			"id": 8127376294006,
			"product_id": 759791747190,
			"title": "6 / RED",
			"price": "7.00",
			"sku": "S17W-4200008099-CAL-6",
			"position": 1,
			"inventory_policy": "deny",
			"compare_at_price": "15.00",
			"fulfillment_service": "manual",
			"inventory_management": "shopify",
			"option1": "6",
			"option2": "RED",
			"option3": null,
			"created_at": "2018-04-23T19:47:58+01:00",
			"updated_at": "2018-06-20T03:40:52+01:00",
			"taxable": false,
			"barcode": null,
			"grams": 100,
			"image_id": null,
			"inventory_quantity": 13,
			"weight": 100,
			"weight_unit": "g",
			"inventory_item_id": 8274804834422,
			"tax_code": "",
			"old_inventory_quantity": 13,
			"requires_shipping": true
      },
      {
			"id": 8127376326774,
			"product_id": 759791747190,
			"title": "8 / Black",
			"price": "12.00",
			"sku": "S17W-4200008099-CAL-8",
			"position": 2,
			"inventory_policy": "deny",
			"compare_at_price": null,
			"fulfillment_service": "manual",
			"inventory_management": "shopify",
			"option1": "8",
			"option2": "Black",
			"option3": null,
			"created_at": "2018-04-23T19:47:58+01:00",
			"updated_at": "2018-06-20T02:58:33+01:00",
			"taxable": false,
			"barcode": null,
			"grams": 100,
			"image_id": null,
			"inventory_quantity": 32,
			"weight": 100,
			"weight_unit": "g",
			"inventory_item_id": 8274804899958,
			"tax_code": "",
			"old_inventory_quantity": 32,
			"requires_shipping": true
      },
      {
			"id": 8127376359542,
			"product_id": 759791747190,
			"title": "10 / Black",
			"price": "12.00",
			"sku": "S17W-4200008099-CAL-10",
			"position": 3,
			"inventory_policy": "deny",
			"compare_at_price": null,
			"fulfillment_service": "manual",
			"inventory_management": "shopify",
			"option1": "10",
			"option2": "Black",
			"option3": null,
			"created_at": "2018-04-23T19:47:58+01:00",
			"updated_at": "2018-06-20T02:58:33+01:00",
			"taxable": false,
			"barcode": null,
			"grams": 100,
			"image_id": null,
			"inventory_quantity": 39,
			"weight": 100,
			"weight_unit": "g",
			"inventory_item_id": 8274805031030,
			"tax_code": "",
			"old_inventory_quantity": 39,
			"requires_shipping": true
      },
      {
			"id": 8127376392310,
			"product_id": 759791747190,
			"title": "12 / Black",
			"price": "12.00",
			"sku": "S17W-4200008099-CAL-12",
			"position": 4,
			"inventory_policy": "deny",
			"compare_at_price": null,
			"fulfillment_service": "manual",
			"inventory_management": "shopify",
			"option1": "12",
			"option2": "Black",
			"option3": null,
			"created_at": "2018-04-23T19:47:58+01:00",
			"updated_at": "2018-06-20T02:58:33+01:00",
			"taxable": false,
			"barcode": null,
			"grams": 100,
			"image_id": null,
			"inventory_quantity": 23,
			"weight": 100,
			"weight_unit": "g",
			"inventory_item_id": 8274805096566,
			"tax_code": "",
			"old_inventory_quantity": 23,
			"requires_shipping": true
      },
      {
			"id": 8127376425078,
			"product_id": 759791747190,
			"title": "14 / Black",
			"price": "12.00",
			"sku": "S17W-4200008099-CAL-14",
			"position": 5,
			"inventory_policy": "deny",
			"compare_at_price": null,
			"fulfillment_service": "manual",
			"inventory_management": "shopify",
			"option1": "14",
			"option2": "Black",
			"option3": null,
			"created_at": "2018-04-23T19:47:58+01:00",
			"updated_at": "2018-06-20T02:58:33+01:00",
			"taxable": false,
			"barcode": null,
			"grams": 100,
			"image_id": null,
			"inventory_quantity": 12,
			"weight": 100,
			"weight_unit": "g",
			"inventory_item_id": 8274805194870,
			"tax_code": "",
			"old_inventory_quantity": 12,
			"requires_shipping": true
      },
      {
			"id": 8127376457846,
			"product_id": 759791747190,
			"title": "16 / RED",
			"price": "7.00",
			"sku": "S17W-4200008099-CAL-16",
			"position": 6,
			"inventory_policy": "deny",
			"compare_at_price": "15.00",
			"fulfillment_service": "manual",
			"inventory_management": "shopify",
			"option1": "16",
			"option2": "RED",
			"option3": null,
			"created_at": "2018-04-23T19:47:58+01:00",
			"updated_at": "2018-06-20T03:40:52+01:00",
			"taxable": false,
			"barcode": null,
			"grams": 100,
			"image_id": null,
			"inventory_quantity": 0,
			"weight": 100,
			"weight_unit": "g",
			"inventory_item_id": 8274805260406,
			"tax_code": "",
			"old_inventory_quantity": 0,
			"requires_shipping": true
      }
    ],
		"options": [
      {
			"id": 1346993127542,
			"product_id": 759791747190,
			"name": "SIZE",
			"position": 1,
			"values": ["6", "8", "10", "12", "14", "16"]
      },
      {
			"id": 2094125613174,
			"product_id": 759791747190,
			"name": "Colour",
			"position": 2,
			"values": ["RED", "Black"]
      }
    ],
		"images": [
      {
			"id": 4306089902198,
			"product_id": 759791747190,
			"position": 1,
			"created_at": "2018-06-20T02:58:32+01:00",
			"updated_at": "2018-06-20T02:58:32+01:00",
			"alt": null,
			"width": 1399,
			"height": 2098,
			"src": "https://cdn.shopify.com/s/files/1/1962/2013/products/S17W-4200008099-CAL-RESHOOT-1.jpg?v=1529459912",
			"variant_ids": []
      },
      {
			"id": 4306089934966,
			"product_id": 759791747190,
			"position": 2,
			"created_at": "2018-06-20T02:58:33+01:00",
			"updated_at": "2018-06-20T02:58:33+01:00",
			"alt": null,
			"width": 1399,
			"height": 2098,
			"src": "https://cdn.shopify.com/s/files/1/1962/2013/products/S17W-4200008099-CAL-RESHOOT-2.jpg?v=1529459913",
			"variant_ids": []
      }
    ],
		"image": {
			"id": 4306089902198,
			"product_id": 759791747190,
			"position": 1,
			"created_at": "2018-06-20T02:58:32+01:00",
			"updated_at": "2018-06-20T02:58:32+01:00",
			"alt": null,
			"width": 1399,
			"height": 2098,
			"src": "https://cdn.shopify.com/s/files/1/1962/2013/products/S17W-4200008099-CAL-RESHOOT-1.jpg?v=1529459912",
			"variant_ids": []
		  }
    },
    {
		"id": 759791911030,
		"title": "3 Strap Mesh Bikini Bottom",
		"body_html": "<p>Look mesmerising in mesh. These bikini bottoms feature a super cute 3 strap mesh detailing. Team with our matching 3 strap mesh bikini top and strappy sandals to complete the look.\r</p><p>Bikini bottom <br>3 strap mesh detail <br>Mesh finish </p>",
		"vendor": "PURE FASHION",
		"product_type": "SWIMWEAR",
		"created_at": "2018-04-23T19:47:58+01:00",
		"handle": "3-strap-mesh-bikini-bottom-bright-yellow-jl3665",
		"updated_at": "2018-06-20T09:52:10+01:00",
		"published_at": "2018-06-17T21:38:53+01:00",
		"template_suffix": null,
		"tags": "/Collections/Clothing, 12, 14, 6, 8, <£10, APItagIndexRemoveThis, Bikini, Bright Yellow, Holiday, Holiday Shop, ISAWITFIRST.com, Mesh, Pcat-Swimwear, RT_.04, Sale, Sale:SALE:New In Clothing, Scat-Swimsuit, Swimwear, XP_425, YELLOW",
		"published_scope": "web",
		"variants": [
      {
			"id": 8127377211510,
			"product_id": 759791911030,
			"title": "6 / YELLOW",
			"price": "7.00",
			"sku": "S17W-4200008100-HEW-6",
			"position": 1,
			"inventory_policy": "deny",
			"compare_at_price": "15.00",
			"fulfillment_service": "manual",
			"inventory_management": "shopify",
			"option1": "6",
			"option2": "YELLOW",
			"option3": null,
			"created_at": "2018-04-23T19:47:58+01:00",
			"updated_at": "2018-06-20T03:40:52+01:00",
			"taxable": false,
			"barcode": null,
			"grams": 100,
			"image_id": null,
			"inventory_quantity": 12,
			"weight": 100,
			"weight_unit": "g",
			"inventory_item_id": 8274805850230,
			"tax_code": "",
			"old_inventory_quantity": 12,
			"requires_shipping": true
      },
      {
			"id": 8127377244278,
			"product_id": 759791911030,
			"title": "8 / Black",
			"price": "12.00",
			"sku": "S17W-4200008100-HEW-8",
			"position": 2,
			"inventory_policy": "deny",
			"compare_at_price": null,
			"fulfillment_service": "manual",
			"inventory_management": "shopify",
			"option1": "8",
			"option2": "Black",
			"option3": null,
			"created_at": "2018-04-23T19:47:58+01:00",
			"updated_at": "2018-06-20T02:58:59+01:00",
			"taxable": false,
			"barcode": null,
			"grams": 100,
			"image_id": null,
			"inventory_quantity": 28,
			"weight": 100,
			"weight_unit": "g",
			"inventory_item_id": 8274805882998,
			"tax_code": "",
			"old_inventory_quantity": 28,
			"requires_shipping": true
      },
      {
			"id": 8127377277046,
			"product_id": 759791911030,
			"title": "10 / Black",
			"price": "12.00",
			"sku": "S17W-4200008100-HEW-10",
			"position": 3,
			"inventory_policy": "deny",
			"compare_at_price": null,
			"fulfillment_service": "manual",
			"inventory_management": "shopify",
			"option1": "10",
			"option2": "Black",
			"option3": null,
			"created_at": "2018-04-23T19:47:58+01:00",
			"updated_at": "2018-06-20T02:58:59+01:00",
			"taxable": false,
			"barcode": null,
			"grams": 100,
			"image_id": null,
			"inventory_quantity": 36,
			"weight": 100,
			"weight_unit": "g",
			"inventory_item_id": 8274805915766,
			"tax_code": "",
			"old_inventory_quantity": 36,
			"requires_shipping": true
      },
      {
			"id": 8127377309814,
			"product_id": 759791911030,
			"title": "12 / Black",
			"price": "12.00",
			"sku": "S17W-4200008100-HEW-12",
			"position": 4,
			"inventory_policy": "deny",
			"compare_at_price": null,
			"fulfillment_service": "manual",
			"inventory_management": "shopify",
			"option1": "12",
			"option2": "Black",
			"option3": null,
			"created_at": "2018-04-23T19:47:58+01:00",
			"updated_at": "2018-06-20T02:58:59+01:00",
			"taxable": false,
			"barcode": null,
			"grams": 100,
			"image_id": null,
			"inventory_quantity": 20,
			"weight": 100,
			"weight_unit": "g",
			"inventory_item_id": 8274805948534,
			"tax_code": "",
			"old_inventory_quantity": 20,
			"requires_shipping": true
      },
      {
			"id": 8127377342582,
			"product_id": 759791911030,
			"title": "14 / Black",
			"price": "12.00",
			"sku": "S17W-4200008100-HEW-14",
			"position": 5,
			"inventory_policy": "deny",
			"compare_at_price": null,
			"fulfillment_service": "manual",
			"inventory_management": "shopify",
			"option1": "14",
			"option2": "Black",
			"option3": null,
			"created_at": "2018-04-23T19:47:58+01:00",
			"updated_at": "2018-06-20T02:58:59+01:00",
			"taxable": false,
			"barcode": null,
			"grams": 100,
			"image_id": null,
			"inventory_quantity": 10,
			"weight": 100,
			"weight_unit": "g",
			"inventory_item_id": 8274805981302,
			"tax_code": "",
			"old_inventory_quantity": 10,
			"requires_shipping": true
      },
      {
			"id": 8127377375350,
			"product_id": 759791911030,
			"title": "16 / YELLOW",
			"price": "7.00",
			"sku": "S17W-4200008100-HEW-16",
			"position": 6,
			"inventory_policy": "deny",
			"compare_at_price": "15.00",
			"fulfillment_service": "manual",
			"inventory_management": "shopify",
			"option1": "16",
			"option2": "YELLOW",
			"option3": null,
			"created_at": "2018-04-23T19:47:58+01:00",
			"updated_at": "2018-06-20T03:40:52+01:00",
			"taxable": false,
			"barcode": null,
			"grams": 100,
			"image_id": null,
			"inventory_quantity": 0,
			"weight": 100,
			"weight_unit": "g",
			"inventory_item_id": 8274806014070,
			"tax_code": "",
			"old_inventory_quantity": 0,
			"requires_shipping": true
      }
    ],
		"options": [
      {
			"id": 1346993324150,
			"product_id": 759791911030,
			"name": "SIZE",
			"position": 1,
			"values": ["6", "8", "10", "12", "14", "16"]
      },
      {
			"id": 2094128595062,
			"product_id": 759791911030,
			"name": "Colour",
			"position": 2,
			"values": ["YELLOW", "Black"]
      }
    ],
		"images": [
      {
			"id": 4306097602678,
			"product_id": 759791911030,
			"position": 1,
			"created_at": "2018-06-20T02:58:59+01:00",
			"updated_at": "2018-06-20T02:58:59+01:00",
			"alt": null,
			"width": 1399,
			"height": 2098,
			"src": "https://cdn.shopify.com/s/files/1/1962/2013/products/S17W-4200008100-HEW-1.jpg?v=1529459939",
			"variant_ids": []
      },
      {
			"id": 4306097635446,
			"product_id": 759791911030,
			"position": 2,
			"created_at": "2018-06-20T02:58:59+01:00",
			"updated_at": "2018-06-20T02:58:59+01:00",
			"alt": null,
			"width": 1399,
			"height": 2098,
			"src": "https://cdn.shopify.com/s/files/1/1962/2013/products/S17W-4200008100-HEW-2.jpg?v=1529459939",
			"variant_ids": []
      }
    ],
		"image": {
			"id": 4306097602678,
			"product_id": 759791911030,
			"position": 1,
			"created_at": "2018-06-20T02:58:59+01:00",
			"updated_at": "2018-06-20T02:58:59+01:00",
			"alt": null,
			"width": 1399,
			"height": 2098,
			"src": "https://cdn.shopify.com/s/files/1/1962/2013/products/S17W-4200008100-HEW-1.jpg?v=1529459939",
			"variant_ids": []
		  }
    },
    {
		"id": 148855816201,
		"title": "3 Strap Mesh Bikini Top",
		"body_html": "<p>Look mesmerising in mesh. These bikini bottoms feature a super cute 3 strap mesh detailing. Team with our matching 3 strap mesh bikini bottoms and strappy sandals to complete the look.\r</p><p>Bikini top<br>3 strap mesh finish <br>Sleeveless<br>Tie up back detail </p>",
		"vendor": "PURE FASHION",
		"product_type": "SWIMWEAR",
		"created_at": "2018-01-13T09:59:42+00:00",
		"handle": "3-strap-mesh-bikini-top-dark-green-jl3662",
		"updated_at": "2018-06-20T03:33:15+01:00",
		"published_at": null,
		"template_suffix": null,
		"tags": ".5, /Collections/Clothing, 10, 12, 14, 50% Off, 6, 8, APItagIndexRemoveThis, Bikini, Dark Green, GREEN, Holiday, Holiday Shop, ISAWITFIRST.com, Mesh, Pcat-Swimwear, RT_.01, Sale, Sale:SALE:New In Clothing, Scat-Swimsuit, Swimwear, XP_475",
		"published_scope": "web",
		"variants": [
      {
			"id": 1748136820745,
			"product_id": 148855816201,
			"title": "6 / GREEN",
			"price": "4.00",
			"sku": "S17W-4200008087-KKI-6",
			"position": 1,
			"inventory_policy": "deny",
			"compare_at_price": "14.00",
			"fulfillment_service": "manual",
			"inventory_management": "shopify",
			"option1": "6",
			"option2": "GREEN",
			"option3": null,
			"created_at": "2018-01-13T09:59:43+00:00",
			"updated_at": "2018-06-20T03:33:15+01:00",
			"taxable": false,
			"barcode": null,
			"grams": 100,
			"image_id": null,
			"inventory_quantity": 0,
			"weight": 100,
			"weight_unit": "g",
			"inventory_item_id": 1814697902089,
			"tax_code": "",
			"old_inventory_quantity": 0,
			"requires_shipping": true
      },
      {
			"id": 1748136853513,
			"product_id": 148855816201,
			"title": "8 / GREEN",
			"price": "3.50",
			"sku": "S17W-4200008087-KKI-8",
			"position": 2,
			"inventory_policy": "deny",
			"compare_at_price": "14.00",
			"fulfillment_service": "manual",
			"inventory_management": "shopify",
			"option1": "8",
			"option2": "GREEN",
			"option3": null,
			"created_at": "2018-01-13T09:59:43+00:00",
			"updated_at": "2018-06-12T17:31:54+01:00",
			"taxable": false,
			"barcode": null,
			"grams": 100,
			"image_id": null,
			"inventory_quantity": 0,
			"weight": 100,
			"weight_unit": "g",
			"inventory_item_id": 1814697934857,
			"tax_code": "",
			"old_inventory_quantity": 0,
			"requires_shipping": true
      },
      {
			"id": 1748136886281,
			"product_id": 148855816201,
			"title": "10 / GREEN",
			"price": "3.50",
			"sku": "S17W-4200008087-KKI-10",
			"position": 3,
			"inventory_policy": "deny",
			"compare_at_price": "14.00",
			"fulfillment_service": "manual",
			"inventory_management": "shopify",
			"option1": "10",
			"option2": "GREEN",
			"option3": null,
			"created_at": "2018-01-13T09:59:43+00:00",
			"updated_at": "2018-06-12T17:31:54+01:00",
			"taxable": false,
			"barcode": null,
			"grams": 100,
			"image_id": null,
			"inventory_quantity": 0,
			"weight": 100,
			"weight_unit": "g",
			"inventory_item_id": 1814697967625,
			"tax_code": "",
			"old_inventory_quantity": 0,
			"requires_shipping": true
      },
      {
			"id": 1748136919049,
			"product_id": 148855816201,
			"title": "12 / GREEN",
			"price": "3.50",
			"sku": "S17W-4200008087-KKI-12",
			"position": 4,
			"inventory_policy": "deny",
			"compare_at_price": "14.00",
			"fulfillment_service": "manual",
			"inventory_management": "shopify",
			"option1": "12",
			"option2": "GREEN",
			"option3": null,
			"created_at": "2018-01-13T09:59:43+00:00",
			"updated_at": "2018-06-12T17:31:54+01:00",
			"taxable": false,
			"barcode": null,
			"grams": 100,
			"image_id": null,
			"inventory_quantity": 0,
			"weight": 100,
			"weight_unit": "g",
			"inventory_item_id": 1814698000393,
			"tax_code": "",
			"old_inventory_quantity": 0,
			"requires_shipping": true
      },
      {
			"id": 1748136951817,
			"product_id": 148855816201,
			"title": "14 / GREEN",
			"price": "3.50",
			"sku": "S17W-4200008087-KKI-14",
			"position": 5,
			"inventory_policy": "deny",
			"compare_at_price": "14.00",
			"fulfillment_service": "manual",
			"inventory_management": "shopify",
			"option1": "14",
			"option2": "GREEN",
			"option3": null,
			"created_at": "2018-01-13T09:59:43+00:00",
			"updated_at": "2018-06-12T17:31:54+01:00",
			"taxable": false,
			"barcode": null,
			"grams": 100,
			"image_id": null,
			"inventory_quantity": 0,
			"weight": 100,
			"weight_unit": "g",
			"inventory_item_id": 1814698033161,
			"tax_code": "",
			"old_inventory_quantity": 0,
			"requires_shipping": true
      },
      {
			"id": 1748136984585,
			"product_id": 148855816201,
			"title": "16 / GREEN",
			"price": "4.00",
			"sku": "S17W-4200008087-KKI-16",
			"position": 6,
			"inventory_policy": "deny",
			"compare_at_price": "14.00",
			"fulfillment_service": "manual",
			"inventory_management": "shopify",
			"option1": "16",
			"option2": "GREEN",
			"option3": null,
			"created_at": "2018-01-13T09:59:43+00:00",
			"updated_at": "2018-06-20T03:33:15+01:00",
			"taxable": false,
			"barcode": null,
			"grams": 100,
			"image_id": null,
			"inventory_quantity": 0,
			"weight": 100,
			"weight_unit": "g",
			"inventory_item_id": 1814698065929,
			"tax_code": "",
			"old_inventory_quantity": 0,
			"requires_shipping": true
      }
    ],
		"options": [
      {
			"id": 225044070409,
			"product_id": 148855816201,
			"name": "SIZE",
			"position": 1,
			"values": ["6", "8", "10", "12", "14", "16"]
      },
      {
			"id": 287035228169,
			"product_id": 148855816201,
			"name": "Colour",
			"position": 2,
			"values": ["GREEN"]
      }
    ],
		"images": [
      {
			"id": 4305626202230,
			"product_id": 148855816201,
			"position": 1,
			"created_at": "2018-06-20T02:38:27+01:00",
			"updated_at": "2018-06-20T02:38:27+01:00",
			"alt": null,
			"width": 1399,
			"height": 2098,
			"src": "https://cdn.shopify.com/s/files/1/1962/2013/products/S17W-4200008087-KKI-1r.jpg?v=1529458707",
			"variant_ids": []
      },
      {
			"id": 4305626234998,
			"product_id": 148855816201,
			"position": 2,
			"created_at": "2018-06-20T02:38:27+01:00",
			"updated_at": "2018-06-20T02:38:27+01:00",
			"alt": null,
			"width": 1399,
			"height": 2098,
			"src": "https://cdn.shopify.com/s/files/1/1962/2013/products/S17W-4200008087-KKI-4r_7c004e17-1dec-426f-95bf-abbca49bb4d4.jpg?v=1529458707",
			"variant_ids": []
      }
    ],
		"image": {
			"id": 4305626202230,
			"product_id": 148855816201,
			"position": 1,
			"created_at": "2018-06-20T02:38:27+01:00",
			"updated_at": "2018-06-20T02:38:27+01:00",
			"alt": null,
			"width": 1399,
			"height": 2098,
			"src": "https://cdn.shopify.com/s/files/1/1962/2013/products/S17W-4200008087-KKI-1r.jpg?v=1529458707",
			"variant_ids": []
		  }
    },
    {
		"id": 759791878262,
		"title": "3 Strap Mesh Bikini Top",
		"body_html": "<p>Catch those rays and top up that tan in this gorgeous 3 strap detail bikini top. Featuring a stylish mesh finish, v neckline and tie up back detail. Team with our matching bikini bottoms and cute sandals to compliment this look. \r</p><p>Bikini top<br>Sleeveless<br>V neck <br>3 strap detail <br>Mesh finish </p>",
		"vendor": "PURE FASHION",
		"product_type": "SWIMWEAR",
		"created_at": "2018-04-23T19:47:57+01:00",
		"handle": "3-strap-mesh-bikini-top-coral-jl3662",
		"updated_at": "2018-06-20T03:40:52+01:00",
		"published_at": "2018-06-19T18:36:48+01:00",
		"template_suffix": null,
		"tags": "12, 14, 6, 8, <£10, APItagIndexRemoveThis, Bikini, Coral, Holiday, Holiday Shop, ISAWITFIRST.com, Mesh, Pcat-Swimwear, RED, RT_.1, Sale, Sale:/Collections/New-In, SALE:New In Clothing, Scat-Swimsuit, Sleeveless, Summer Shop Aug, Swimwear, V Neck, XP_475",
		"published_scope": "web",
		"variants": [
      {
			"id": 8127376752758,
			"product_id": 759791878262,
			"title": "6 / RED",
			"price": "7.00",
			"sku": "S17W-4200008088-CAL-6",
			"position": 1,
			"inventory_policy": "deny",
			"compare_at_price": "15.00",
			"fulfillment_service": "manual",
			"inventory_management": "shopify",
			"option1": "6",
			"option2": "RED",
			"option3": null,
			"created_at": "2018-04-23T19:47:58+01:00",
			"updated_at": "2018-06-20T03:40:52+01:00",
			"taxable": false,
			"barcode": null,
			"grams": 100,
			"image_id": null,
			"inventory_quantity": 7,
			"weight": 100,
			"weight_unit": "g",
			"inventory_item_id": 8274805522550,
			"tax_code": "",
			"old_inventory_quantity": 7,
			"requires_shipping": true
      },
      {
			"id": 8127376883830,
			"product_id": 759791878262,
			"title": "8 / Black",
			"price": "12.00",
			"sku": "S17W-4200008088-CAL-8",
			"position": 2,
			"inventory_policy": "deny",
			"compare_at_price": null,
			"fulfillment_service": "manual",
			"inventory_management": "shopify",
			"option1": "8",
			"option2": "Black",
			"option3": null,
			"created_at": "2018-04-23T19:47:58+01:00",
			"updated_at": "2018-06-20T02:59:13+01:00",
			"taxable": false,
			"barcode": null,
			"grams": 100,
			"image_id": null,
			"inventory_quantity": 21,
			"weight": 100,
			"weight_unit": "g",
			"inventory_item_id": 8274805588086,
			"tax_code": "",
			"old_inventory_quantity": 21,
			"requires_shipping": true
      },
      {
			"id": 8127376916598,
			"product_id": 759791878262,
			"title": "10 / Black",
			"price": "12.00",
			"sku": "S17W-4200008088-CAL-10",
			"position": 3,
			"inventory_policy": "deny",
			"compare_at_price": null,
			"fulfillment_service": "manual",
			"inventory_management": "shopify",
			"option1": "10",
			"option2": "Black",
			"option3": null,
			"created_at": "2018-04-23T19:47:58+01:00",
			"updated_at": "2018-06-20T02:59:13+01:00",
			"taxable": false,
			"barcode": null,
			"grams": 100,
			"image_id": null,
			"inventory_quantity": 23,
			"weight": 100,
			"weight_unit": "g",
			"inventory_item_id": 8274805686390,
			"tax_code": "",
			"old_inventory_quantity": 23,
			"requires_shipping": true
      },
      {
			"id": 8127376982134,
			"product_id": 759791878262,
			"title": "12 / Black",
			"price": "12.00",
			"sku": "S17W-4200008088-CAL-12",
			"position": 4,
			"inventory_policy": "deny",
			"compare_at_price": null,
			"fulfillment_service": "manual",
			"inventory_management": "shopify",
			"option1": "12",
			"option2": "Black",
			"option3": null,
			"created_at": "2018-04-23T19:47:58+01:00",
			"updated_at": "2018-06-20T02:59:13+01:00",
			"taxable": false,
			"barcode": null,
			"grams": 100,
			"image_id": null,
			"inventory_quantity": 13,
			"weight": 100,
			"weight_unit": "g",
			"inventory_item_id": 8274805719158,
			"tax_code": "",
			"old_inventory_quantity": 13,
			"requires_shipping": true
      },
      {
			"id": 8127377047670,
			"product_id": 759791878262,
			"title": "14 / Black",
			"price": "12.00",
			"sku": "S17W-4200008088-CAL-14",
			"position": 5,
			"inventory_policy": "deny",
			"compare_at_price": null,
			"fulfillment_service": "manual",
			"inventory_management": "shopify",
			"option1": "14",
			"option2": "Black",
			"option3": null,
			"created_at": "2018-04-23T19:47:58+01:00",
			"updated_at": "2018-06-20T02:59:13+01:00",
			"taxable": false,
			"barcode": null,
			"grams": 100,
			"image_id": null,
			"inventory_quantity": 7,
			"weight": 100,
			"weight_unit": "g",
			"inventory_item_id": 8274805784694,
			"tax_code": "",
			"old_inventory_quantity": 7,
			"requires_shipping": true
      },
      {
			"id": 8127377113206,
			"product_id": 759791878262,
			"title": "16 / RED",
			"price": "7.00",
			"sku": "S17W-4200008088-CAL-16",
			"position": 6,
			"inventory_policy": "deny",
			"compare_at_price": "15.00",
			"fulfillment_service": "manual",
			"inventory_management": "shopify",
			"option1": "16",
			"option2": "RED",
			"option3": null,
			"created_at": "2018-04-23T19:47:58+01:00",
			"updated_at": "2018-06-20T03:40:52+01:00",
			"taxable": false,
			"barcode": null,
			"grams": 100,
			"image_id": null,
			"inventory_quantity": 0,
			"weight": 100,
			"weight_unit": "g",
			"inventory_item_id": 8274805817462,
			"tax_code": "",
			"old_inventory_quantity": 0,
			"requires_shipping": true
      }
    ],
		"options": [
      {
			"id": 1346993291382,
			"product_id": 759791878262,
			"name": "SIZE",
			"position": 1,
			"values": ["6", "8", "10", "12", "14", "16"]
      },
      {
			"id": 2094130987126,
			"product_id": 759791878262,
			"name": "Colour",
			"position": 2,
			"values": ["RED", "Black"]
      }
    ],
		"images": [
      {
			"id": 4306103304310,
			"product_id": 759791878262,
			"position": 1,
			"created_at": "2018-06-20T02:59:13+01:00",
			"updated_at": "2018-06-20T02:59:13+01:00",
			"alt": null,
			"width": 1399,
			"height": 2098,
			"src": "https://cdn.shopify.com/s/files/1/1962/2013/products/S17W-4200008088-CAL-RESHOOT-1.jpg?v=1529459953",
			"variant_ids": []
      },
      {
			"id": 4306103337078,
			"product_id": 759791878262,
			"position": 2,
			"created_at": "2018-06-20T02:59:13+01:00",
			"updated_at": "2018-06-20T02:59:13+01:00",
			"alt": null,
			"width": 1399,
			"height": 2098,
			"src": "https://cdn.shopify.com/s/files/1/1962/2013/products/S17W-4200008088-CAL-RESHOOT-2.jpg?v=1529459953",
			"variant_ids": []
      }
    ],
		"image": {
			"id": 4306103304310,
			"product_id": 759791878262,
			"position": 1,
			"created_at": "2018-06-20T02:59:13+01:00",
			"updated_at": "2018-06-20T02:59:13+01:00",
			"alt": null,
			"width": 1399,
			"height": 2098,
			"src": "https://cdn.shopify.com/s/files/1/1962/2013/products/S17W-4200008088-CAL-RESHOOT-1.jpg?v=1529459953",
			"variant_ids": []
		  }
    }
  ]
}
